gripe/__init__.py
gripe/__main__.py
gripe/_version.py
gripe/bin.py
gripe/util/__init__.py
gripe-2024.2.24.1.31.dist-info/METADATA
gripe-2024.2.24.1.31.dist-info/WHEEL
gripe-2024.2.24.1.31.dist-info/entry_points.txt
gripe-2024.2.24.1.31.dist-info/top_level.txt
gripe-2024.2.24.1.31.dist-info/RECORD
