Metadata-Version: 2.1
Name: gripe
Version: 2024.2.24.1.31
Summary: Shell helper utilities for python
Home-page: https://github.com/elo-enterprises/gripe/
Author: elo
License: MIT
Project-URL: Documentation, https://github.com/elo-enterprises/gripe/
Project-URL: Source, https://github.com/elo-enterprises/gripe/
Project-URL: Download, https://github.com/elo-enterprises/gripe/#files
Platform: any
Classifier: Programming Language :: Python
Requires-Python: >3.7
Requires-Dist: grip ==4.6.1
Requires-Dist: psutil ==5.9.5
Requires-Dist: fleks >=2024.2.9.23.58
Provides-Extra: dev
Requires-Dist: IPython ; extra == 'dev'
Provides-Extra: lint
Requires-Dist: tox ; extra == 'lint'
Provides-Extra: publish
Requires-Dist: twine ; extra == 'publish'
Provides-Extra: testing
Requires-Dist: IPython ; extra == 'testing'
Requires-Dist: tox ; extra == 'testing'
Requires-Dist: pytest ; extra == 'testing'
Requires-Dist: pytest-cov ; extra == 'testing'
Requires-Dist: mock ; extra == 'testing'
Requires-Dist: flake8 ==5.0.4 ; extra == 'testing'
